variationalsparsebayes/__init__.py
variationalsparsebayes/sparse_bnn.py
variationalsparsebayes/sparse_glm.py
variationalsparsebayes/svi_half_cauchy.py
variationalsparsebayes-0.3.1.dist-info/LICENSE
variationalsparsebayes-0.3.1.dist-info/METADATA
variationalsparsebayes-0.3.1.dist-info/WHEEL
variationalsparsebayes-0.3.1.dist-info/RECORD
