Metadata-Version: 2.1
Name: variationalsparsebayes
Version: 0.3.1
Summary: Stochastic variational inference with sparsity inducing priors in PyTorch.
License: GNUv3
Author: Kevin Course
Author-email: kevin.course@mail.utoronto.ca
Requires-Python: >=3.10,<3.12
Classifier: License :: Other/Proprietary License
Classifier: Programming Language :: Python :: 3
Classifier: Programming Language :: Python :: 3.10
Classifier: Programming Language :: Python :: 3.11
Requires-Dist: numpy (>=1.26.1,<2.0.0)
Requires-Dist: torch (>=2.1.0,<3.0.0)
